brill.py
Brill-0.1.dist-info/METADATA
Brill-0.1.dist-info/RECORD
Brill-0.1.dist-info/WHEEL
Brill-0.1.dist-info/top_level.txt
