Metadata-Version: 2.1
Name: Brill
Version: 0.1
Summary: The Brill API
Home-page: https://gitlab.com/brillpublishers
Author: Etienne Posthumus
Author-email: posthumus@brill.com
License: UNKNOWN
Platform: UNKNOWN
Classifier: Programming Language :: Python :: 3
Classifier: Operating System :: OS Independent
